restart_mongo/filter.py
restart_mongo/paginator.py
restart_mongo/sorter.py
restart_mongo/utils.py
restart_mongo/__init__.py
restart_mongo/form.py
restart_mongo/collection.py
restart_mongo/selector.py
restart_mongo/middlewares.py
restart_mongo/ext/file.py
restart_mongo/ext/renderers.py
restart_mongo/ext/__init__.py
restart_mongo/ext/dufilter.py
restart_mongo/ext/files.py
RESTArt_Mongo-0.1.4.dist-info/WHEEL
RESTArt_Mongo-0.1.4.dist-info/RECORD
RESTArt_Mongo-0.1.4.dist-info/METADATA
RESTArt_Mongo-0.1.4.dist-info/metadata.json
RESTArt_Mongo-0.1.4.dist-info/top_level.txt
RESTArt_Mongo-0.1.4.dist-info/DESCRIPTION.rst
