Metadata-Version: 2.0
Name: RESTArt-Mongo
Version: 0.1.4
Summary: A RESTArt extension for using MongoDB.
Home-page: https://github.com/RussellLuo/restart-mongo
Author: RussellLuo
Author-email: luopeng.he@gmail.com
License: MIT
Keywords: REST APIs,Python
Platform: UNKNOWN
Requires-Dist: python-restart
Requires-Dist: pymongo (==2.7.2)
Requires-Dist: jsonpatch (==1.7)
Requires-Dist: JsonForm (>=0.0.2)
Requires-Dist: JsonSir (>=0.0.2)
